relic/sga/v2/__init__.py
relic/sga/v2/_util.py
relic/sga/v2/cli.py
relic/sga/v2/definitions.py
relic/sga/v2/py.typed
relic/sga/v2/serialization.py
relic/sga/v2/arciv/__init__.py
relic/sga/v2/arciv/definitions.py
relic/sga/v2/arciv/errors.py
relic/sga/v2/arciv/lexer.py
relic/sga/v2/arciv/parser.py
relic/sga/v2/arciv/py.typed
relic/sga/v2/arciv/writer.py
relic/sga/v2/essencefs/__init__.py
relic/sga/v2/essencefs/definitions.py
relic/sga/v2/essencefs/opener.py
relic/sga/v2/essencefs/pathing.py
relic/sga/v2/essencefs/py.typed
relic_tool_sga_v2-2.1.0.dist-info/LICENSE.txt
relic_tool_sga_v2-2.1.0.dist-info/METADATA
relic_tool_sga_v2-2.1.0.dist-info/WHEEL
relic_tool_sga_v2-2.1.0.dist-info/entry_points.txt
relic_tool_sga_v2-2.1.0.dist-info/top_level.txt
relic_tool_sga_v2-2.1.0.dist-info/RECORD
