Metadata-Version: 2.2
Name: relic-tool-sga-v2
Version: 2.1.0
Summary: A plugin to read/write Relic SGA (V2) archive files.
Author: Marcus Kertesz
Project-URL: Bug Tracker, https://github.com/MAK-Relic-Tool/Issues-Tracker/issues
Project-URL: Homepage, https://github.com/MAK-Relic-Tool/Relic-Tool-SGA-V2
Classifier: Programming Language :: Python :: 3 :: Only
Classifier: Programming Language :: Python :: 3.9
Classifier: Programming Language :: Python :: 3.10
Classifier: Programming Language :: Python :: 3.11
Classifier: Programming Language :: Python :: 3.12
Classifier: Programming Language :: Python :: 3.13
Classifier: License :: OSI Approved :: GNU General Public License v3 (GPLv3)
Requires-Python: >=3.9
License-File: LICENSE.txt
Requires-Dist: relic-tool-sga-core>=2.0.0
Requires-Dist: ply>=3.11
Requires-Dist: relic-tool-core>=2.3.0
